.gitignore
.gitmodules
.travis.yml
.woodpecker.yaml
AUTHORS
CHANGES.rst
LICENSE
MANIFEST.in
README.rst
setup.cfg
setup.py
.ci/get_sundials.sh
.ci/patch_001_sund400.diff
.ci/run-matrix.sh
.ci/test-case.sh
.ci/test-sdist.sh
.circleci/config.yml
.gh-pages-skeleton/.nojekyll
conda-recipe/bld.bat
conda-recipe/build.sh
conda-recipe/meta.yaml
conda-recipe/run_test.py
examples/van_der_pol.ipynb
examples/van_der_pol.png
examples/van_der_pol.py
examples/tests/test_examples.py
external/anyode/LICENSE
external/anyode/cython_def/anyode.pxd
external/anyode/cython_def/anyode_numpy.pxd
external/anyode/include/anyode/anyode.hpp
external/anyode/include/anyode/anyode_blas_lapack.hpp
external/anyode/include/anyode/anyode_blasless.hpp
external/anyode/include/anyode/anyode_buffer.hpp
external/anyode/include/anyode/anyode_decomposition.hpp
external/anyode/include/anyode/anyode_decomposition_lapack.hpp
external/anyode/include/anyode/anyode_iterative.hpp
external/anyode/include/anyode/anyode_matrix.hpp
external/anyode/include/anyode/anyode_numpy.hpp
external/anyode/include/anyode/anyode_numpy_types.hpp
external/anyode/include/anyode/anyode_parallel.hpp
external/anyode/include/anyode/anyode_util.hpp
pycvodes/__init__.py
pycvodes/_cvodes.cpp
pycvodes/_cvodes.pyx
pycvodes/_libs.py
pycvodes/_release.py
pycvodes/_types.py
pycvodes/_util.py
pycvodes.egg-info/PKG-INFO
pycvodes.egg-info/SOURCES.txt
pycvodes.egg-info/dependency_links.txt
pycvodes.egg-info/requires.txt
pycvodes.egg-info/top_level.txt
pycvodes/include/cvodes_anyode.hpp
pycvodes/include/cvodes_anyode.pxd
pycvodes/include/cvodes_anyode_nogil.pxd
pycvodes/include/cvodes_anyode_numpy.hpp
pycvodes/include/cvodes_anyode_numpy.pxd
pycvodes/include/cvodes_anyode_parallel.hpp
pycvodes/include/cvodes_anyode_parallel.pxd
pycvodes/include/cvodes_cxx.hpp
pycvodes/include/cvodes_cxx.pxd
pycvodes/include/sundials_cxx.hpp
pycvodes/tests/__init__.py
pycvodes/tests/test_cvodes_numpy.py
scripts/build-conda-recipe-using-docker.sh
scripts/check_clean_repo_on_master.sh
scripts/coverage_badge.py
scripts/generate_docs.sh
scripts/post_release.sh
scripts/prepare_deploy.sh
scripts/rasterize.js
scripts/release.sh
